MapColoniesJSONLogger/__init__.py
MapColoniesJSONLogger/logger.py
MapColoniesJSONLogger-1.0.0.dist-info/METADATA
MapColoniesJSONLogger-1.0.0.dist-info/WHEEL
MapColoniesJSONLogger-1.0.0.dist-info/top_level.txt
MapColoniesJSONLogger-1.0.0.dist-info/RECORD
