Metadata-Version: 2.1
Name: MapColoniesJSONLogger
Version: 1.0.0
Summary: A JSON logger for map colonies project
Home-page: https://github.com/MapColonies/json-logger
Author: MapColonies
Author-email: mapcolonies@gmail.com
License: UNKNOWN
Platform: UNKNOWN
Classifier: Programming Language :: Python :: 3
Classifier: License :: OSI Approved :: MIT License
Classifier: Operating System :: OS Independent
Requires-Python: >=3.6
Requires-Dist: ecs-logging (==0.5.0)
